<?xml version="1.0" encoding="UTF-8"?>
<metadata xml:lang="zh"><Esri><CreaDate>20220228</CreaDate><CreaTime>10243600</CreaTime><ArcGISFormat>1.0</ArcGISFormat><SyncOnce>TRUE</SyncOnce><DataProperties><lineage><Process ToolSource="d:\program files\geoscene\pro\Resources\ArcToolbox\toolboxes\Data Management Tools.tbx\CreateFeatureclass" Date="20220228" Time="102436">CreateFeatureclass D:\MyData\GIS\K1067 Station 点 # 否 否 "GEOGCS['GCS_CGCS_2000',DATUM['D_2000',SPHEROID['S_2000',6378137.0,298.257222101004]],PRIMEM['Greenwich',0.0],UNIT['Degree',0.0174532925199433]];-400 -400 11258999068426.2;-100000 10000;-100000 10000;8.98315284119521E-09;0.001;0.001;IsHighPrecision" # 0 0 0 #</Process><Process ToolSource="d:\program files\geoscene\pro\Resources\ArcToolbox\Toolboxes\Data Management Tools.tbx\UpdateSchema" Date="20220228" Time="105054">UpdateSchema "CIMDATA=&lt;CIMStandardDataConnection xsi:type='typens:CIMStandardDataConnection' xmlns:xsi='http://www.w3.org/2001/XMLSchema-instance' xmlns:xs='http://www.w3.org/2001/XMLSchema' xmlns:typens='http://www.esri.com/schemas/ArcGIS/2.5.0'&gt;&lt;WorkspaceConnectionString&gt;DATABASE=D:\MyData\GIS\K1067&lt;/WorkspaceConnectionString&gt;&lt;WorkspaceFactory&gt;Shapefile&lt;/WorkspaceFactory&gt;&lt;Dataset&gt;Station&lt;/Dataset&gt;&lt;DatasetType&gt;esriDTFeatureClass&lt;/DatasetType&gt;&lt;/CIMStandardDataConnection&gt;" &lt;operationSequence&gt;&lt;workflow&gt;&lt;AddField&gt;&lt;field_name&gt;站名&lt;/field_name&gt;&lt;field_type&gt;TEXT&lt;/field_type&gt;&lt;field_length&gt;255&lt;/field_length&gt;&lt;field_is_nullable&gt;False&lt;/field_is_nullable&gt;&lt;field_is_required&gt;False&lt;/field_is_required&gt;&lt;/AddField&gt;&lt;/workflow&gt;&lt;/operationSequence&gt;</Process></lineage></DataProperties></Esri></metadata>
